gee_package/__init__.py
gee_package/arithmetic.py
gee_package-0.1.dist-info/METADATA
gee_package-0.1.dist-info/WHEEL
gee_package-0.1.dist-info/top_level.txt
gee_package-0.1.dist-info/RECORD
