Metadata-Version: 2.1
Name: gee_package
Version: 0.1
Summary: A simple arithmetic operations package
Author: Your Name
Author-email: your.email@example.com
Classifier: Programming Language :: Python :: 3
Classifier: License :: OSI Approved :: MIT License
Classifier: Operating System :: OS Independent
Requires-Python: >=3.6
